{
  "runtime_id": 5350,
  "types": {
    "Balance": "u128",
    "Index": "u32",
    "Phase": "frame_system.Phase",
    "Address": "sp_runtime.multiaddress.MultiAddress",
    "ExtrinsicSignature": "sp_runtime.MultiSignature",
    "ParaId": "polkadot_parachain.primitives.Id",
    "crab_parachain_runtime.Event": "GenericEvent",
    "dp_common_runtime.remote_governance.pallet.Call": "GenericCall",
    "sp_core.crypto.AccountId32": "GenericAccountId",
    "pallet_identity.types.Data": "Data"
  },
  "versioning": []
}